thefuzz/StringMatcher.py
thefuzz/__init__.py
thefuzz/fuzz.py
thefuzz/process.py
thefuzz/string_processing.py
thefuzz/utils.py
thefuzz-0.20.0.dist-info/LICENSE.txt
thefuzz-0.20.0.dist-info/METADATA
thefuzz-0.20.0.dist-info/WHEEL
thefuzz-0.20.0.dist-info/top_level.txt
thefuzz-0.20.0.dist-info/zip-safe
thefuzz-0.20.0.dist-info/RECORD
