Metadata-Version: 2.1
Name: thefuzz
Version: 0.20.0
Summary: Fuzzy string matching in python
Home-page: https://github.com/seatgeek/thefuzz
Author: Adam Cohen
Author-email: adam@seatgeek.com
License: GPLv2
Platform: UNKNOWN
Classifier: Intended Audience :: Developers
Classifier: License :: OSI Approved :: GNU General Public License v2 (GPLv2)
Classifier: Programming Language :: Python
Classifier: Programming Language :: Python :: 3
Classifier: Programming Language :: Python :: 3.7
Classifier: Programming Language :: Python :: 3.8
Classifier: Programming Language :: Python :: 3.9
Classifier: Programming Language :: Python :: 3.10
Classifier: Programming Language :: Python :: 3.11
Classifier: Programming Language :: Python :: 3 :: Only
Requires-Python: >=3.7
Provides-Extra: speedup
License-File: LICENSE.txt
